libgsea
