Metadata-Version: 1.1
Name: libgsea
Version: 0.5.0
Summary: Library for GSEA including extended GSEA.
Home-page: https://github.com/antonybholmes/libgsea
Author: Antony B Holmes
Author-email: antony.b.holmes@gmail.com
License: UNKNOWN
Platform: UNKNOWN
Classifier: Programming Language :: Python :: 3
Classifier: License :: OSI Approved :: MIT License
Classifier: Operating System :: OS Independent
